conf/__init__.py
conf/settings.py
terraform_resource_tags_check-0.1.0.dist-info/METADATA
terraform_resource_tags_check-0.1.0.dist-info/WHEEL
terraform_resource_tags_check-0.1.0.dist-info/top_level.txt
terraform_resource_tags_check-0.1.0.dist-info/RECORD
