Metadata-Version: 2.1
Name: terraform-resource-tags-check
Version: 0.1.0
Requires-Dist: checkov
